LICENSE
MANIFEST.in
README.md
VERSION
setup.cfg
setup.py
src/cltl.brain.egg-info/PKG-INFO
src/cltl.brain.egg-info/SOURCES.txt
src/cltl.brain.egg-info/dependency_links.txt
src/cltl.brain.egg-info/requires.txt
src/cltl.brain.egg-info/top_level.txt
src/cltl/brain/LTM_context_processing.py
src/cltl/brain/LTM_experience_processing.py
src/cltl/brain/LTM_mention_processing.py
src/cltl/brain/LTM_question_processing.py
src/cltl/brain/LTM_shared.py
src/cltl/brain/LTM_statement_processing.py
src/cltl/brain/__init__.py
src/cltl/brain/basic_brain.py
src/cltl/brain/fame_aware.py
src/cltl/brain/long_term_memory.py
src/cltl/brain/infrastructure/__init__.py
src/cltl/brain/infrastructure/api.py
src/cltl/brain/infrastructure/rdf_builder.py
src/cltl/brain/infrastructure/store_connector.py
src/cltl/brain/ontologies/BASIC-REPOSITORY-CONFIG-GRAPHDB.ttl
src/cltl/brain/ontologies/blackbox_dataset.csv
src/cltl/brain/ontologies/catalog-v001.xml
src/cltl/brain/ontologies/ceo_original.owl
src/cltl/brain/ontologies/ceo_original.ttl
src/cltl/brain/ontologies/eps.ttl
src/cltl/brain/ontologies/gaf_extended.ttl
src/cltl/brain/ontologies/gaf_original.rdf
src/cltl/brain/ontologies/grasp_extended.ttl
src/cltl/brain/ontologies/grasp_original.rdf
src/cltl/brain/ontologies/integration.jsonld
src/cltl/brain/ontologies/integration.ttl
src/cltl/brain/ontologies/integration_context.jsonld
src/cltl/brain/ontologies/n2mu.ttl
src/cltl/brain/ontologies/n2mu_sensory.ttl
src/cltl/brain/ontologies/prov-dc.ttl
src/cltl/brain/ontologies/prov-dictionary.ttl
src/cltl/brain/ontologies/prov-links.ttl
src/cltl/brain/ontologies/prov-o-inverses.ttl
src/cltl/brain/ontologies/prov-o.ttl
src/cltl/brain/ontologies/sem_extended.ttl
src/cltl/brain/ontologies/sem_original.rdf
src/cltl/brain/queries/count_of_type.rq
src/cltl/brain/queries/famous_person.rq
src/cltl/brain/queries/one_to_one_conflicts.rq
src/cltl/brain/queries/prefixes.rq
src/cltl/brain/queries/content_exploration/all_negation_conflicts.rq
src/cltl/brain/queries/content_exploration/best_friends.rq
src/cltl/brain/queries/content_exploration/count_friends.rq
src/cltl/brain/queries/content_exploration/count_instances.rq
