Metadata-Version: 2.1
Name: cltl.brain
Version: 1.0.dev2
Summary: The Leolani Brain module for knowledge representation
Home-page: https://github.com/leolani/cltl-knowledgerepresentation
License: MIT License
Requires-Python: >=3.7
Provides-Extra: service
License-File: LICENSE
